{
  "book": "Evangelicon",
  "chapter": 13,
  "verse_start": 36,
  "verse_end": 39,
  "blurb": "Lostness is less about distance than about being missed. The shepherd here does not grumble at the extra work; he is joy-scarred by what would be missing had even one remained astray. Each repentant soul adds another gleam to the banquet feast, and every little celebration echoes the larger one at the heart of God. Go find your next sheep today—you may discover the rejoicing starts the moment you set out.",
  "verses": [
    {
      "verse": "36",
      "text": "Now all the publicans and sinners were coming near unto him, to hear him."
    },
    {
      "verse": "37",
      "text": "And the Pharisees and scribes murmured, saying, This man receiveth sinners, and eateth with them."
    },
    {
      "verse": "38",
      "text": "And he spake this parable unto them, saying,"
    },
    {
      "verse": "39",
      "text": "What man of you, having an hundred sheep, if he lose one of them, doth not leave the ninety and nine in the wilderness, and go after that which is lost, until he find it?"
    }
  ],
  "date": "2026-05-16"
}