{
  "book": "Philadelphians",
  "chapter": "4",
  "verse_start": "1",
  "verse_end": "4",
  "verses": [
    {
      "verse": "1",
      "text": "Abstain from noxious herbs, which are not the husbandry of Jesus Christ, because they are not the planting of the Father."
    },
    {
      "verse": "2",
      "text": "Not that I have found division among you, but filtering."
    },
    {
      "verse": "3",
      "text": "For as many as are of God and of Jesus Christ, they are with the bishop;"
    },
    {
      "verse": "4",
      "text": "And as many as shall repent and enter into the unity of the Church, these also shall be of God, that they may be living after Jesus Christ."
    }
  ],
  "date": "2026-06-18"
}